LICENSE
README.md
setup.py
fastapi_watchlog_apm/__init__.py
fastapi_watchlog_apm/collector.py
fastapi_watchlog_apm/error_handler.py
fastapi_watchlog_apm/middleware.py
fastapi_watchlog_apm/sender.py
fastapi_watchlog_apm.egg-info/PKG-INFO
fastapi_watchlog_apm.egg-info/SOURCES.txt
fastapi_watchlog_apm.egg-info/dependency_links.txt
fastapi_watchlog_apm.egg-info/requires.txt
fastapi_watchlog_apm.egg-info/top_level.txt