Metadata-Version: 2.1
Name: fastapi_watchlog_apm
Version: 1.0.2
Summary: Lightweight APM for FastAPI that sends metrics to Watchlog Agent
Home-page: https://github.com/Watchlog-monitoring/fastapi_watchlog_apm
Author: Mohammadreza
Author-email: mohammadnajm75@gmail.com
Classifier: Programming Language :: Python :: 3
Classifier: Framework :: FastAPI
Classifier: License :: OSI Approved :: MIT License
Classifier: Operating System :: OS Independent
Requires-Python: >=3.7
License-File: LICENSE
Requires-Dist: fastapi
Requires-Dist: starlette
Requires-Dist: psutil
Requires-Dist: requests
